siri_parser-0.1.8.dist-info/METADATA
siri_parser-0.1.8.dist-info/WHEEL
siri_parser-0.1.8.dist-info/licenses/license
siri_parser.libs/libgcc_s-b5472b99.so.1
siri_parser/__init__.py
siri_parser/siri_parser.abi3.so
siri_parser-0.1.8.dist-info/RECORD
